micro_center_price_monitor/__init__.py
micro_center_price_monitor/__main__.py
micro_center_price_monitor/custom_exceptions.py
micro_center_price_monitor/data.py
micro_center_price_monitor/mail.py
micro_center_price_monitor/price_checker.py
micro_center_price_monitor/scraper.py
micro_center_price_monitor-0.0.6.dist-info/LICENSE.txt
micro_center_price_monitor-0.0.6.dist-info/METADATA
micro_center_price_monitor-0.0.6.dist-info/WHEEL
micro_center_price_monitor-0.0.6.dist-info/entry_points.txt
micro_center_price_monitor-0.0.6.dist-info/top_level.txt
micro_center_price_monitor-0.0.6.dist-info/RECORD
