Metadata-Version: 2.1
Name: micro-center-price-monitor
Version: 0.0.6
Summary: Price monitor tool for Micro Center
Home-page: https://github.com/Nintendude64/micro-center-price-monitor
Author: Martin Daniels
Author-email: martindaniels02@gmail.com
License: UNKNOWN
Platform: UNKNOWN
Classifier: Programming Language :: Python :: 3
Classifier: Programming Language :: Python :: 3.6
Classifier: Programming Language :: Python :: 3.7
Classifier: License :: OSI Approved :: GNU General Public License v2 or later (GPLv2+)
Classifier: Operating System :: OS Independent
Provides-Extra: dev
Requires-Dist: beautifulsoup4 (>==4.7.1) ; extra == 'dev'
Requires-Dist: bs4 (==0.0.1) ; extra == 'dev'
Requires-Dist: lxml (==4.3.4) ; extra == 'dev'
Requires-Dist: requests (==2.22.0) ; extra == 'dev'
